[
  {
    "id": 1,
    "name": "Bebidas",
    "row": [
      {
        "id": 1,
        "subcategoria": "Águas"
      },
      {
        "id": 2,
        "subcategoria": "Refrigerantes"
      }
    ]
  },
  {
    "id": 2,
    "name": "Mercearia",
    "row": [
      {
        "id": 1,
        "subcategoria": "Arroz"
      },
      {
        "id": 2,
        "subcategoria": "Massa"
      }
    ]
  },
  {
    "id": 3,
    "name": "Alimentação",
    "row": [
      {
        "id": 1,
        "subcategoria": "Pizza"
      },
      {
        "id": 2,
        "subcategoria": "Lasanha"
      }
    ]
  }
]